pstorch/__init__.py
pstorch/trainer.py
pstorch-0.1.2.dist-info/METADATA
pstorch-0.1.2.dist-info/WHEEL
pstorch-0.1.2.dist-info/top_level.txt
pstorch-0.1.2.dist-info/RECORD
